Workbook
Name Aporte: Simulador!$D$14:$D$14
Name Patrimonio: Simulador!$D$17:$D$17
Name Qtde_anos: Simulador!$D$15:$D$15
Name Rendimento_carteira: Simulador!$D$10:$D$10
Name Sugestao_investimento: Simulador!$D$11:$D$11
Name Taxa_mensal: Simulador!$D$16:$D$16

Sheet Simulador
B8: Configurações
B9: Salário | D9: 2000
B10: Rendimento da carteira | D10: 0.006
B11: Sugestões de investimento (30%) | D11: =D9*30% -> 600
B13: Investimento Mensal
B14: Quanto investir por mês? | D14: 200
B15: Por quantos anos? | D15: 5
B16: Taxa de rendimento mensal? | D16: 0.01079
B17: Patrimônio acumulado? | D17: {=FV(Taxa_mensal,Qtde_anos*12,Aporte*(-1))} -> 16755.383
B18: Dividendos mensais? | D18: {=Patrimonio*Rendimento_carteira} -> 100.5323
B20: Cenários | D20: Dividendos
A21: 2 | B21: Quanto em 2 anos? | C21: =FV($D$16,$A21*12,$D$14*-1) -> 5445.5255 | D21: {=C21*Rendimento_carteira} -> 32.673153
A22: 5 | B22: Quanto em 5 anos? | C22: =FV($D$16,$A22*12,$D$14*-1) -> 16755.383 | D22: {=C22*Rendimento_carteira} -> 100.5323
A23: 10 | B23: Quanto em 10 anos? | C23: =FV($D$16,$A23*12,$D$14*-1) -> 48656.843 | D23: {=C23*Rendimento_carteira} -> 291.94106
A24: 20 | B24: Quanto em 20 anos? | C24: =FV($D$16,$A24*12,$D$14*-1) -> 225039.68 | D24: {=C24*Rendimento_carteira} -> 1350.2381
A25: 30 | B25: Quanto em 30 anos? | C25: =FV($D$16,$A25*12,$D$14*-1) -> 864433.93 | D25: {=C25*Rendimento_carteira} -> 5186.6036
B29: Perfil | C29: Agressivo
B30: Valor a ser investido por mês | C30: {=Aporte} -> 200
B32: Tipos de FIIs | C32: Percentual sugerido | D32: Valores
B33: Papel | C33: =VLOOKUP($C$29&"-"&B33,tbl_apoio!B:E,4,FALSE) -> 0.5 | D33: =$C$30*C33 -> 100
B34: Tijolo | C34: =VLOOKUP($C$29&"-"&B34,tbl_apoio!B:E,4,FALSE) -> 0.1 | D34: =$C$30*C34 -> 20
B35: Híbridos | C35: =VLOOKUP($C$29&"-"&B35,tbl_apoio!B:E,4,FALSE) -> 0.05 | D35: =$C$30*C35 -> 10
B36: FOFs | C36: =VLOOKUP($C$29&"-"&B36,tbl_apoio!B:E,4,FALSE) -> 0.05 | D36: =$C$30*C36 -> 10
B37: Desenvolvimento | C37: =VLOOKUP($C$29&"-"&B37,tbl_apoio!B:E,4,FALSE) -> 0.2 | D37: =$C$30*C37 -> 40
B38: Hotelaria | C38: =VLOOKUP($C$29&"-"&B38,tbl_apoio!B:E,4,FALSE) -> 0.1 | D38: =$C$30*C38 -> 20
D39: =SUM(D33:D38) -> 200

Sheet tbl_apoio
B2: Chave composta | C2: Perfil | D2: Tipos de FIIs | E2: %
B3: =C3&"-"&D3 -> Conservador-Papel | C3: Conservador | D3: Papel | E3: 0.3
B4: =C4&"-"&D4 -> Conservador-Tijolo | C4: Conservador | D4: Tijolo | E4: 0.5
B5: =C5&"-"&D5 -> Conservador-Híbridos | C5: Conservador | D5: Híbridos | E5: 0.1
B6: =C6&"-"&D6 -> Conservador-FOFs | C6: Conservador | D6: FOFs | E6: 0.1
B7: =C7&"-"&D7 -> Conservador-Desenvolvimento | C7: Conservador | D7: Desenvolvimento | E7: 0
B8: =C8&"-"&D8 -> Conservador-Hotelaria | C8: Conservador | D8: Hotelaria | E8: 0
B9: =C9&"-"&D9 -> Moderado-Papel | C9: Moderado | D9: Papel | E9: 0.32
B10: =C10&"-"&D10 -> Moderado-Tijolo | C10: Moderado | D10: Tijolo | E10: 0.35
B11: =C11&"-"&D11 -> Moderado-Híbridos | C11: Moderado | D11: Híbridos | E11: 0.08
B12: =C12&"-"&D12 -> Moderado-FOFs | C12: Moderado | D12: FOFs | E12: 0.05
B13: =C13&"-"&D13 -> Moderado-Desenvolvimento | C13: Moderado | D13: Desenvolvimento | E13: 0.1
B14: =C14&"-"&D14 -> Moderado-Hotelaria | C14: Moderado | D14: Hotelaria | E14: 0.1
... B20: =C20&"-"&D20 -> Agressivo-Hotelaria | C20: Agressivo | D20: Hotelaria | E20: 0.1
